LICENSE
README.md
setup.cfg
setup.py
vmray/integration_kit/__init__.py
vmray/integration_kit/integration_kit.py
vmray/rest_api/__init__.py
vmray/rest_api/rest_api.py
vmray/rest_api/version.py
vmray_rest_api.egg-info/PKG-INFO
vmray_rest_api.egg-info/SOURCES.txt
vmray_rest_api.egg-info/dependency_links.txt
vmray_rest_api.egg-info/not-zip-safe
vmray_rest_api.egg-info/requires.txt
vmray_rest_api.egg-info/top_level.txt