Metadata-Version: 2.1
Name: vmray-rest-api
Version: 5.2.1
Summary: VMRay REST API Client and Integration Kit
Home-page: https://www.vmray.com
Author: VMRay
Author-email: info@vmray.com
License: Proprietary
Platform: UNKNOWN
Classifier: Programming Language :: Python :: 3
Classifier: Programming Language :: Python :: 3.6
Requires-Python: >=3.6
License-File: LICENSE
